read_exec_cep/__init__.py
read_exec_cep/read_exec.py
read_exec_cep-0.0.1.dist-info/METADATA
read_exec_cep-0.0.1.dist-info/WHEEL
read_exec_cep-0.0.1.dist-info/licenses/LICENSE
read_exec_cep-0.0.1.dist-info/RECORD
